soda/scientific/anomaly_detection/anomaly_detector.py
soda/scientific/anomaly_detection/detector_config.yaml
soda/scientific/anomaly_detection/feedback_processor.py
soda/scientific/anomaly_detection/models/__init__.py
soda/scientific/anomaly_detection/models/base.py
soda/scientific/anomaly_detection/models/prophet_model.py
soda/scientific/anomaly_detection_v2/anomaly_detector.py
soda/scientific/anomaly_detection_v2/detector_config.yaml
soda/scientific/anomaly_detection_v2/exceptions.py
soda/scientific/anomaly_detection_v2/feedback_processor.py
soda/scientific/anomaly_detection_v2/frequency_detector.py
soda/scientific/anomaly_detection_v2/globals.py
soda/scientific/anomaly_detection_v2/pydantic_models.py
soda/scientific/anomaly_detection_v2/utils.py
soda/scientific/anomaly_detection_v2/models/__init__.py
soda/scientific/anomaly_detection_v2/models/base.py
soda/scientific/anomaly_detection_v2/models/prophet_model.py
soda/scientific/anomaly_detection_v2/simulate/anomaly_detection_dataset.py
soda/scientific/anomaly_detection_v2/simulate/app.py
soda/scientific/anomaly_detection_v2/simulate/globals.py
soda/scientific/anomaly_detection_v2/simulate/pydantic_models.py
soda/scientific/anomaly_detection_v2/simulate/visualisation.py
soda/scientific/anomaly_detection_v2/simulate/assets/SODA.svg
soda/scientific/anomaly_detection_v2/simulate/assets/favicon.ico
soda/scientific/common/exceptions.py
soda/scientific/distribution/comparison.py
soda/scientific/distribution/generate_dro.py
soda/scientific/distribution/utils.py
soda_core_scientific-3.5.6.dist-info/LICENSE
soda_core_scientific-3.5.6.dist-info/METADATA
soda_core_scientific-3.5.6.dist-info/WHEEL
soda_core_scientific-3.5.6.dist-info/top_level.txt
soda_core_scientific-3.5.6.dist-info/RECORD
