Metadata-Version: 2.1
Name: soda-core-scientific
Version: 3.5.6
License-File: LICENSE
Requires-Dist: soda-core==3.5.6
Requires-Dist: pandas<2.0.0
Requires-Dist: wheel
Requires-Dist: pydantic<3.0.0,>=2.0.0
Requires-Dist: scipy>=1.8.0
Requires-Dist: numpy<2.0.0,>=1.23.3
Requires-Dist: inflection==0.5.1
Requires-Dist: httpx<2.0.0,>=0.18.1
Requires-Dist: PyYAML<7.0.0,>=5.4.1
Requires-Dist: cython>=0.22
Requires-Dist: prophet<2.0.0,>=1.1.5
Provides-Extra: simulator
Requires-Dist: streamlit<2.0.0,>=1.30.0; extra == "simulator"
Requires-Dist: plotly>=5.18.0; extra == "simulator"
